xRevChatGPT/ChatGPT.py
xRevChatGPT/__init__.py
xRevChatGPT/__main__.py
xRevChatGPT-0.0.49.dist-info/LICENSE
xRevChatGPT-0.0.49.dist-info/METADATA
xRevChatGPT-0.0.49.dist-info/WHEEL
xRevChatGPT-0.0.49.dist-info/entry_points.txt
xRevChatGPT-0.0.49.dist-info/top_level.txt
xRevChatGPT-0.0.49.dist-info/RECORD
