Metadata-Version: 2.1
Name: xRevChatGPT
Version: 0.0.49
Summary: ChatGPT is a reverse engineering of OpenAI's ChatGPT API
Author: Antonio Cheong
Author-email: acheong@student.dalat.org
License: GNU General Public License v2.0
License-File: LICENSE
Requires-Dist: undetected-chromedriver (>=3.1.7)
Requires-Dist: selenium (>=4.7.2)
Requires-Dist: tls-client (>=0.1.7)
Requires-Dist: 2captcha-python (>=1.1.3)
